{
    "variants": {
        "size": {
            "icon": "arrows-out",
            "label": "Size"
        }
    },
    "props": {
        "color": {
            "icon": "paint-bucket",
            "label": "Color",
            "visible": true,
            "group": {
                "indicator-color": {
                    "icon": "circle-notch",
                    "label": "Indicator color",
                    "visible": true
                }
            }
        },
        "size": {
            "icon": "arrows-out",
            "label": "Size",
            "visible": true,
            "group": {
                "size": {
                    "icon": "arrows-up-down",
                    "label": "Size",
                    "visible": true,
                    "propertyType": "slider",
                    "range": [
                        8,
                        100
                    ],
                    "step": 1
                },
                "border-radius": {
                    "icon": "corners-out",
                    "label": "Border radius",
                    "visible": true
                },
                "thickness": {
                    "icon": "pencil-line",
                    "label": "Thickness",
                    "visible": true,
                    "propertyType": "slider",
                    "range": [
                        1,
                        30
                    ],
                    "step": 1
                }
            }
        }
    }
}