{
  "props": {
    "thumb": {
      "icon": "sliders-horizontal",
      "label": "Thumb",
      "visible": true,
      "group": {
        "thumb-selected": {
          "label": "Thumb selected",
          "visible": true
        },
        "thumb-unselected": {
          "label": "Thumb unselected",
          "visible": true
        },
        "thumb-height": {
          "label": "Thumb height",
          "visible": true
        },
        "thumb-width": {
          "label": "Thumb width",
          "visible": true
        },
        "thumb-border-radius": {
          "label": "Thumb corner radius",
          "visible": true
        }
      }
    },
    "track": {
      "icon": "faders-horizontal",
      "label": "Track",
      "visible": true,
      "group": {
        "track-selected": {
          "label": "Track selected",
          "visible": true
        },
        "track-unselected": {
          "label": "Track unselected",
          "visible": true
        },
        "track-width": {
          "label": "Track width",
          "visible": true
        },
        "track-inner-padding": {
          "label": "Track inner padding",
          "visible": true
        },
        "track-border-radius": {
          "label": "Track corner radius",
          "visible": true
        }
      }
    },
    "label-switch-gap": {
      "icon": "split-horizontal",
      "label": "Gap between label and switch",
      "visible": true
    },
    "label-text": {
      "icon": "text-aa",
      "label": "Label text style",
      "visible": true
    },
    "thumb-icon": {
      "icon": "diamond",
      "label": "Thumb icon",
      "visible": false,
      "group": {
        "thumb-icon-size": {
          "label": "Size",
          "visible": true
        },
        "thumb-icon-selected": {
          "label": "Selected",
          "visible": true
        },
        "thumb-icon-unselected": {
          "label": "Unselected",
          "visible": true
        }
      }
    },
    "elevation": {
      "icon": "copy-simple",
      "label": "Elevation",
      "visible": true,
      "group": {
        "thumb-elevation": {
          "label": "Thumb",
          "visible": true
        },
        "track-elevation": {
          "label": "Track",
          "visible": true
        }
      }
    }
  }
}
