{
  "tokens": {
    "color": {
      "cornflower": {
        "000": { "$type": "color", "$value": "#eaf7fb" },
        "050": { "$type": "color", "$value": "#a1dfe7" },
        "100": { "$type": "color", "$value": "#73ceda" },
        "200": { "$type": "color", "$value": "#55b9c8" },
        "300": { "$type": "color", "$value": "#359ead" },
        "400": { "$type": "color", "$value": "#007889" },
        "500": { "$type": "color", "$value": "#00636f" },
        "600": { "$type": "color", "$value": "#004f59" },
        "700": { "$type": "color", "$value": "#00363d" },
        "800": { "$type": "color", "$value": "#001f24" },
        "900": { "$type": "color", "$value": "#021316" },
        "1000": { "$type": "color", "$value": "#00090b" }
      },
      "gray": {
        "000": { "$type": "color", "$value": "#fcfcfc" },
        "050": { "$type": "color", "$value": "#f9f9f9" },
        "100": { "$type": "color", "$value": "#e9e9e9" },
        "200": { "$type": "color", "$value": "#d6d6d6" },
        "300": { "$type": "color", "$value": "#c0c0c0" },
        "400": { "$type": "color", "$value": "#999999" },
        "500": { "$type": "color", "$value": "#7d7d7d" },
        "600": { "$type": "color", "$value": "#5f5f5f" },
        "700": { "$type": "color", "$value": "#454545" },
        "800": { "$type": "color", "$value": "#2c2c2c" },
        "900": { "$type": "color", "$value": "#0f0f0f" },
        "1000": { "$type": "color", "$value": "#0a0a0a" }
      },
      "greensheen": {
        "000": { "$type": "color", "$value": "#e9fbf1" },
        "050": { "$type": "color", "$value": "#b8f1cf" },
        "100": { "$type": "color", "$value": "#7be4a5" },
        "200": { "$type": "color", "$value": "#3dd67b" },
        "300": { "$type": "color", "$value": "#00c851" },
        "400": { "$type": "color", "$value": "#00a945" },
        "500": { "$type": "color", "$value": "#008b38" },
        "600": { "$type": "color", "$value": "#006c2c" },
        "700": { "$type": "color", "$value": "#035425" },
        "800": { "$type": "color", "$value": "#013717" },
        "900": { "$type": "color", "$value": "#002b1d" },
        "1000": { "$type": "color", "$value": "#00130d" }
      },
      "mandarin": {
        "000": { "$type": "color", "$value": "#fff4ea" },
        "050": { "$type": "color", "$value": "#ffe7d2" },
        "100": { "$type": "color", "$value": "#fcd2ac" },
        "200": { "$type": "color", "$value": "#fdb981" },
        "300": { "$type": "color", "$value": "#ffa052" },
        "400": { "$type": "color", "$value": "#fc853b" },
        "500": { "$type": "color", "$value": "#fc7527" },
        "600": { "$type": "color", "$value": "#d9510d" },
        "700": { "$type": "color", "$value": "#a84510" },
        "800": { "$type": "color", "$value": "#82360c" },
        "900": { "$type": "color", "$value": "#592208" },
        "1000": { "$type": "color", "$value": "#2a1004" }
      },
      "mandy": {
        "000": { "$type": "color", "$value": "#feeaea" },
        "050": { "$type": "color", "$value": "#fbcfcf" },
        "100": { "$type": "color", "$value": "#f79f9f" },
        "200": { "$type": "color", "$value": "#f46e6e" },
        "300": { "$type": "color", "$value": "#f03e3e" },
        "400": { "$type": "color", "$value": "#ec0e0e" },
        "500": { "$type": "color", "$value": "#d40d0d" },
        "600": { "$type": "color", "$value": "#bd0b0b" },
        "700": { "$type": "color", "$value": "#8e0808" },
        "800": { "$type": "color", "$value": "#5e0606" },
        "900": { "$type": "color", "$value": "#2f0303" },
        "1000": { "$type": "color", "$value": "#1a0606" }
      },
      "salmon": {
        "000": { "$type": "color", "$value": "#fbeff1" },
        "050": { "$type": "color", "$value": "#f6d5d8" },
        "100": { "$type": "color", "$value": "#f8b9bf" },
        "200": { "$type": "color", "$value": "#f8919a" },
        "300": { "$type": "color", "$value": "#e55d78" },
        "400": { "$type": "color", "$value": "#dd2c56" },
        "500": { "$type": "color", "$value": "#d21e49" },
        "600": { "$type": "color", "$value": "#b1173b" },
        "700": { "$type": "color", "$value": "#851a34" },
        "800": { "$type": "color", "$value": "#5e0312" },
        "900": { "$type": "color", "$value": "#4c010d" },
        "1000": { "$type": "color", "$value": "#24060b" }
      }
    },
    "font": {
      "size": {
        "2xs": {
          "$type": "number",
          "$value": 10
        },
        "xs": {
          "$type": "number",
          "$value": 12
        },
        "sm": {
          "$type": "number",
          "$value": 14
        },
        "md": {
          "$type": "number",
          "$value": 16
        },
        "lg": {
          "$type": "number",
          "$value": 18
        },
        "xl": {
          "$type": "number",
          "$value": 20
        },
        "2xl": {
          "$type": "number",
          "$value": 24
        },
        "3xl": {
          "$type": "number",
          "$value": 28
        },
        "4xl": {
          "$type": "number",
          "$value": 32
        },
        "5xl": {
          "$type": "number",
          "$value": 36
        },
        "6xl": {
          "$type": "number",
          "$value": 40
        }
      },
      "family": {
        "lexend": {
          "$type": "fontFamily",
          "$value": "Lexend"
        },
        "quattrocento": {
          "$type": "fontFamily",
          "$value": "Quattrocento"
        },
        "bellota": {
          "$type": "fontFamily",
          "$value": "Bellota Text"
        }
      },
      "letter-spacing": {
        "tighest": {
          "$type": "number",
          "$value": -0.75
        },
        "tighter": {
          "$type": "number",
          "$value": -0.5
        },
        "tight": {
          "$type": "number",
          "$value": -0.25
        },
        "default": {
          "$type": "number",
          "$value": 0
        },
        "wide": {
          "$type": "number",
          "$value": 0.25
        },
        "wider": {
          "$type": "number",
          "$value": 0.5
        },
        "widest": {
          "$type": "number",
          "$value": 0.75
        }
      },
      "weight": {
        "thin": {
          "$type": "number",
          "$value": 100
        },
        "extra-light": {
          "$type": "number",
          "$value": 200
        },
        "light": {
          "$type": "number",
          "$value": 300
        },
        "regular": {
          "$type": "number",
          "$value": 400
        },
        "medium": {
          "$type": "number",
          "$value": 500
        },
        "semi-bold": {
          "$type": "number",
          "$value": 600
        },
        "bold": {
          "$type": "number",
          "$value": 700
        },
        "extra-bold": {
          "$type": "number",
          "$value": 800
        },
        "black": {
          "$type": "number",
          "$value": 900
        }
      }
    },
    "effect": {
      "none": {
        "$type": "number",
        "$value": 0
      },
      "0-5x": {
        "$type": "number",
        "$value": 4
      },
      "default": {
        "$type": "number",
        "$value": 8
      },
      "1-5x": {
        "$type": "number",
        "$value": 12
      },
      "2x": {
        "$type": "number",
        "$value": 16
      },
      "3x": {
        "$type": "number",
        "$value": 24
      },
      "4x": {
        "$type": "number",
        "$value": 32
      },
      "5x": {
        "$type": "number",
        "$value": 40
      },
      "6x": {
        "$type": "number",
        "$value": 48
      }
    },
    "size": {
      "none": {
        "$type": "number",
        "$value": 0
      },
      "0-5x": {
        "$type": "number",
        "$value": 4
      },
      "default": {
        "$type": "number",
        "$value": 8
      },
      "1-5x": {
        "$type": "number",
        "$value": 12
      },
      "2x": {
        "$type": "number",
        "$value": 16
      },
      "3x": {
        "$type": "number",
        "$value": 24
      },
      "4x": {
        "$type": "number",
        "$value": 32
      },
      "5x": {
        "$type": "number",
        "$value": 40
      },
      "6x": {
        "$type": "number",
        "$value": 48
      }
    },
    "opacity": {
      "ghost": {
        "$type": "number",
        "$value": 38
      },
      "faint": {
        "$type": "number",
        "$value": 68
      },
      "veiled": {
        "$type": "number",
        "$value": 84
      },
      "smoky": {
        "$type": "number",
        "$value": 94
      },
      "solid": {
        "$type": "number",
        "$value": 100
      }
    }
  }
}